goenrich
