Metadata-Version: 1.1
Name: goenrich
Version: 1.8.0
Summary: GO enrichment with python -- pandas meets networkx
Home-page: https://github.com/jdrudolph/goenrich
Author: Jan Daniel Rudolph
Author-email: jan.daniel.rudolph@gmail.com
License: MIT
Download-URL: https://github.com/jdrudolph/goenrich/tarball/1.6
Keywords: GO,Gene Ontology,Biology,Enrichment,Bioinformatics,Computational Biology,library,visualization,graphviz,pandas
Platform: UNKNOWN
Classifier: Development Status :: 4 - Beta
Classifier: Intended Audience :: Science/Research
Classifier: License :: OSI Approved :: MIT License
Classifier: Programming Language :: Python :: 3.4
Classifier: Programming Language :: Python :: 2.7
Classifier: Topic :: Scientific/Engineering :: Bio-Informatics
Classifier: Topic :: Software Development :: Libraries
